<?xml version="1.0" encoding="UTF-8"?>
<objects serializationModel="Studio.02.02.00">
	<object class="EncodingSetting" id="{56ce8e6a-514d-41a5-ac14-54f6987a5dc8}">
		<property name="encodingFormat">
			<value>3</value>
		</property>
		<property name="quality">
			<value>37</value>
		</property>
		<relationship name="platform">
			<destination>{10dec311-5e54-40a8-8647-394e9a9b542a}</destination>
		</relationship>
		<relationship name="encodable">
			<destination>{10dec311-5e54-40a8-8647-394e9a9b542a}</destination>
		</relationship>
	</object>
</objects>
